.gitignore
.gitmodules
MANIFEST.in
bootstrap.py
buildout.cfg
setup.py
cc/__init__.py
cc.licenserdf.egg-info/PKG-INFO
cc.licenserdf.egg-info/SOURCES.txt
cc.licenserdf.egg-info/dependency_links.txt
cc.licenserdf.egg-info/entry_points.txt
cc.licenserdf.egg-info/namespace_packages.txt
cc.licenserdf.egg-info/not-zip-safe
cc.licenserdf.egg-info/requires.txt
cc.licenserdf.egg-info/top_level.txt
cc/licenserdf/__init__.py
cc/licenserdf/util.py
cc/licenserdf/licenses/Makefile.am
cc/licenserdf/licenses/creativecommons.org_licenses_BSD_.rdf
cc/licenserdf/licenses/creativecommons.org_licenses_GPL_2.0_.rdf
cc/licenserdf/licenses/creativecommons.org_licenses_LGPL_2.1_.rdf
cc/licenserdf/licenses/creativecommons.org_licenses_MIT_.rdf
cc/licenserdf/licenses/creativecommons.org_licenses_by-nc-nd_2.0_.rdf
cc/licenserdf/licenses/creativecommons.org_licenses_by-nc-nd_2.0_at_.rdf
cc/licenserdf/licenses/creativecommons.org_licenses_by-nc-nd_2.0_au_.rdf
cc/licenserdf/licenses/creativecommons.org_licenses_by-nc-nd_2.0_be_.rdf
cc/licenserdf/licenses/creativecommons.org_licenses_by-nc-nd_2.0_br_.rdf
cc/licenserdf/licenses/creativecommons.org_licenses_by-nc-nd_2.0_ca_.rdf
cc/licenserdf/licenses/creativecommons.org_licenses_by-nc-nd_2.0_cl_.rdf
cc/licenserdf/licenses/creativecommons.org_licenses_by-nc-nd_2.0_de_.rdf
cc/licenserdf/licenses/creativecommons.org_licenses_by-nc-nd_2.0_es_.rdf
cc/licenserdf/licenses/creativecommons.org_licenses_by-nc-nd_2.0_fr_.rdf
cc/licenserdf/licenses/creativecommons.org_licenses_by-nc-nd_2.0_hr_.rdf
cc/licenserdf/licenses/creativecommons.org_licenses_by-nc-nd_2.0_it_.rdf
cc/licenserdf/licenses/creativecommons.org_licenses_by-nc-nd_2.0_jp_.rdf
cc/licenserdf/licenses/creativecommons.org_licenses_by-nc-nd_2.0_kr_.rdf
cc/licenserdf/licenses/creativecommons.org_licenses_by-nc-nd_2.0_nl_.rdf
cc/licenserdf/licenses/creativecommons.org_licenses_by-nc-nd_2.0_pl_.rdf
cc/licenserdf/licenses/creativecommons.org_licenses_by-nc-nd_2.0_tw_.rdf
cc/licenserdf/licenses/creativecommons.org_licenses_by-nc-nd_2.0_uk_.rdf
cc/licenserdf/licenses/creativecommons.org_licenses_by-nc-nd_2.0_za_.rdf
cc/licenserdf/licenses/creativecommons.org_licenses_by-nc-nd_2.1_au_.rdf
cc/licenserdf/licenses/creativecommons.org_licenses_by-nc-nd_2.1_es_.rdf
