Metadata-Version: 1.0
Name: cc.licenserdf
Version: 0.2.29
Summary: Tool scripts for manipulating the license RDF files.
Home-page: http://creativecommons.org
Author: Nathan R. Yergler
Author-email: nathan@creativecommons.org
License: MIT
Platform: UNKNOWN
